chessmaker/__init__.py
chessmaker/chess/__init__.py
chessmaker/chess/base/__init__.py
chessmaker/chess/base/board.py
chessmaker/chess/base/game.py
chessmaker/chess/base/move_option.py
chessmaker/chess/base/piece.py
chessmaker/chess/base/player.py
chessmaker/chess/base/position.py
chessmaker/chess/base/rule.py
chessmaker/chess/base/square.py
chessmaker/chess/game_factory.py
chessmaker/chess/piece_utils.py
chessmaker/chess/pieces/__init__.py
chessmaker/chess/pieces/bishop.py
chessmaker/chess/pieces/king.py
chessmaker/chess/pieces/knight.py
chessmaker/chess/pieces/knook/__init__.py
chessmaker/chess/pieces/knook/knook.py
chessmaker/chess/pieces/knook/knookable.py
chessmaker/chess/pieces/knook/knookable_knight.py
chessmaker/chess/pieces/knook/knookable_rook.py
chessmaker/chess/pieces/knook/merge_to_knook.py
chessmaker/chess/pieces/pawn.py
chessmaker/chess/pieces/queen.py
chessmaker/chess/pieces/rook.py
chessmaker/chess/results/__init__.py
chessmaker/chess/results/capture_all_pieces_to_win.py
chessmaker/chess/results/checkmate.py
chessmaker/chess/results/double_check_to_win.py
chessmaker/chess/results/no_captures_or_pawn_moves.py
chessmaker/chess/results/repetition.py
chessmaker/chess/results/stalemate.py
chessmaker/chess/results/standard_result.py
chessmaker/chess/rules/__init__.py
chessmaker/chess/rules/beta_decay.py
chessmaker/chess/rules/forced_en_passant.py
chessmaker/chess/rules/il_vaticano.py
chessmaker/chess/rules/king_cant_move_to_c2.py
chessmaker/chess/rules/knight_boosting.py
chessmaker/chess/rules/la_bastarda.py
chessmaker/chess/rules/omnipotent_f6_pawn.py
chessmaker/chess/rules/siberian_swipe.py
chessmaker/clients/__init__.py
chessmaker/clients/pywebio_ui.py
chessmaker/cloneable.py
chessmaker/events/__init__.py
chessmaker/events/event.py
chessmaker/events/event_priority.py
chessmaker/events/event_publisher.py
chessmaker-0.4.2.dist-info/LICENSE
chessmaker-0.4.2.dist-info/METADATA
chessmaker-0.4.2.dist-info/WHEEL
chessmaker-0.4.2.dist-info/RECORD
