Metadata-Version: 2.1
Name: chessmaker
Version: 0.4.2
Summary: An easily extendible chess implementation designed to support any custom rule or feature
License: AGPL-3.0-or-later
Keywords: chess
Author: WolfDWyc
Author-email: yoavwolfdw@gmail.com
Requires-Python: >=3.11,<4.0
Classifier: Development Status :: 3 - Alpha
Classifier: License :: OSI Approved :: GNU Affero General Public License v3
Classifier: License :: OSI Approved :: GNU Affero General Public License v3 or later (AGPLv3+)
Classifier: Operating System :: OS Independent
Classifier: Programming Language :: Python
Classifier: Programming Language :: Python :: 3
Classifier: Programming Language :: Python :: 3.11
Classifier: Programming Language :: Python :: 3
Classifier: Programming Language :: Python :: 3.11
Classifier: Topic :: Games/Entertainment :: Board Games
Classifier: Topic :: Games/Entertainment :: Turn Based Strategy
Classifier: Topic :: Software Development :: Libraries :: Python Modules
Requires-Dist: pywebio (==1.7.1)
Requires-Dist: pywebio-battery (==0.4.0)
Project-URL: homepage, https://github.com/WolfDWyc/ChessMaker
